{"version":1,"kind":"Article","sha256":"125ea85562172a2fbf751bb698ddc709023a10e2276e34b7a54a45c294c563d5","slug":"collaboration.ambassador-schemes","location":"/collaboration/ambassador-schemes.md","dependencies":[],"frontmatter":{"title":"Ambassador Schemes","content_includes_title":false,"authors":[{"nameParsed":{"literal":"The Turing Way Community","given":"The Turing Way","family":"Community"},"name":"The Turing Way Community","id":"contributors-myst-generated-uid-0"}],"license":{"content":{"id":"CC-BY-4.0","url":"https://creativecommons.org/licenses/by/4.0/","name":"Creative Commons Attribution 4.0 International","free":true,"CC":true},"code":{"id":"MIT","url":"https://opensource.org/licenses/MIT","name":"MIT License","free":true,"osi":true}},"github":"https://github.com/the-turing-way/the-turing-way","copyright":"2019-2025","numbering":{"title":{"offset":1}},"edit_url":"https://github.com/the-turing-way/the-turing-way/blob/main/book/website/collaboration/ambassador-schemes.md","thumbnail":"/build/peer-learning-e3a29c546d41d0a42998b818bece07d7.jpeg","exports":[{"format":"md","filename":"ambassador-schemes.md","url":"/build/ambassador-schemes-9f30cc62fc1b8328333311c735125f31.md"}]},"mdast":{"type":"root","children":[{"type":"block","children":[{"type":"heading","depth":2,"position":{"start":{"line":5,"column":1},"end":{"line":5,"column":1}},"children":[{"type":"text","value":"Prerequisites","position":{"start":{"line":5,"column":1},"end":{"line":5,"column":1}},"key":"n8g4wCkGpv"}],"label":"cl-ambassador-schemes-prerequisites","identifier":"cl-ambassador-schemes-prerequisites","html_id":"cl-ambassador-schemes-prerequisites","key":"NGtdZnL3kn"},{"type":"table","position":{"start":{"line":7,"column":1},"end":{"line":11,"column":1}},"children":[{"type":"tableRow","position":{"start":{"line":7,"column":1},"end":{"line":7,"column":1}},"children":[{"type":"tableCell","header":true,"position":{"start":{"line":7,"column":1},"end":{"line":7,"column":1}},"children":[{"type":"text","value":"Prerequisites","position":{"start":{"line":7,"column":1},"end":{"line":7,"column":1}},"key":"ydBb3YAceN"}],"key":"VdPI8Cz5yK"},{"type":"tableCell","header":true,"position":{"start":{"line":7,"column":1},"end":{"line":7,"column":1}},"children":[{"type":"text","value":"Importance","position":{"start":{"line":7,"column":1},"end":{"line":7,"column":1}},"key":"vXkCcXr1CI"}],"key":"kYGQQ1gxqA"},{"type":"tableCell","header":true,"position":{"start":{"line":7,"column":1},"end":{"line":7,"column":1}},"children":[{"type":"text","value":"Skill Level","position":{"start":{"line":7,"column":1},"end":{"line":7,"column":1}},"key":"E4EJ0lzwMQ"}],"key":"RnigZQC91E"},{"type":"tableCell","header":true,"position":{"start":{"line":7,"column":1},"end":{"line":7,"column":1}},"children":[{"type":"text","value":"Notes","position":{"start":{"line":7,"column":1},"end":{"line":7,"column":1}},"key":"k9ppU42Zvs"}],"key":"usGAn51n12"}],"key":"CicU5gYFbn"},{"type":"tableRow","position":{"start":{"line":9,"column":1},"end":{"line":9,"column":1}},"children":[{"type":"tableCell","position":{"start":{"line":9,"column":1},"end":{"line":9,"column":1}},"children":[{"type":"link","kind":"ref","identifier":"cl-new-community","label":"cl-new-community","children":[{"type":"text","value":"Managing a New Community and Team","key":"z7krEQSL7n"}],"url":"/collaboration/new-community","internal":true,"dataUrl":"/collaboration.new-community.json","key":"O8nLEQyvmR"}],"key":"BJ1QlzT6xk"},{"type":"tableCell","position":{"start":{"line":1,"column":1},"end":{"line":1,"column":1}},"children":[{"type":"text","value":"Helpful","position":{"start":{"line":1,"column":1},"end":{"line":1,"column":1}},"key":"E8Bxj0vgv0"}],"key":"LQJBHY6c9x"},{"type":"tableCell","position":{"start":{"line":1,"column":1},"end":{"line":1,"column":1}},"children":[{"type":"text","value":"Beginner","position":{"start":{"line":1,"column":1},"end":{"line":1,"column":1}},"key":"cAbraa7OdQ"}],"key":"pBkNyeXGKs"},{"type":"tableCell","position":{"start":{"line":1,"column":1},"end":{"line":1,"column":1}},"children":[{"type":"text","value":"This chapter has lots of useful tips around managing a new community which can apply to ambassador schemes","position":{"start":{"line":1,"column":1},"end":{"line":1,"column":1}},"key":"hGtu6ODGd8"}],"key":"Q3TkCVLK6Q"}],"key":"ZWmbURXQVd"},{"type":"tableRow","position":{"start":{"line":10,"column":1},"end":{"line":10,"column":1}},"children":[{"type":"tableCell","position":{"start":{"line":10,"column":1},"end":{"line":10,"column":1}},"children":[{"type":"link","kind":"ref","identifier":"cl-coworking","label":"cl-coworking","children":[{"type":"text","value":"Organising Coworking Calls or Meetings","key":"rrMDHzzMVG"}],"url":"/collaboration/coworking","internal":true,"dataUrl":"/collaboration.coworking.json","key":"Zc7i1od96B"},{"type":"text","value":" and ","position":{"start":{"line":1,"column":1},"end":{"line":1,"column":1}},"key":"NPDTdBVeYp"},{"type":"link","kind":"ref","identifier":"cl-chairing","label":"cl-chairing","children":[{"type":"text","value":"Chairing Events","key":"JaYzm9vJqg"}],"url":"/collaboration/chairing","internal":true,"dataUrl":"/collaboration.chairing.json","key":"ziLTnN3Ob9"}],"key":"JKVID4TBHK"},{"type":"tableCell","position":{"start":{"line":1,"column":1},"end":{"line":1,"column":1}},"children":[{"type":"text","value":"Helpful","position":{"start":{"line":1,"column":1},"end":{"line":1,"column":1}},"key":"mAS9cZZjeX"}],"key":"DRZ3viDG9P"},{"type":"tableCell","position":{"start":{"line":1,"column":1},"end":{"line":1,"column":1}},"children":[{"type":"text","value":"Beginner","position":{"start":{"line":1,"column":1},"end":{"line":1,"column":1}},"key":"uYv6dmLKdp"}],"key":"P5UUn8iIi6"},{"type":"tableCell","position":{"start":{"line":1,"column":1},"end":{"line":1,"column":1}},"children":[{"type":"text","value":"These chapters may be useful if you are planning to host events and/or co-working during an ambassador scheme","position":{"start":{"line":1,"column":1},"end":{"line":1,"column":1}},"key":"mThKjFgcUq"}],"key":"KzBegdUnPv"}],"key":"F9Cxsh2Q8A"},{"type":"tableRow","position":{"start":{"line":11,"column":1},"end":{"line":11,"column":1}},"children":[{"type":"tableCell","position":{"start":{"line":11,"column":1},"end":{"line":11,"column":1}},"children":[{"type":"link","kind":"ref","identifier":"cl-event-tools","label":"cl-event-tools","children":[{"type":"text","value":"Tools for Collaboration","key":"VRmXL7jpyH"}],"url":"/collaboration/event-tools","internal":true,"dataUrl":"/collaboration.event-tools.json","key":"Ckj8QlmyQQ"}],"key":"zRbqy5zrHL"},{"type":"tableCell","position":{"start":{"line":1,"column":1},"end":{"line":1,"column":1}},"children":[{"type":"text","value":"Helpful","position":{"start":{"line":1,"column":1},"end":{"line":1,"column":1}},"key":"Nsby6xXp8P"}],"key":"PMGfrKHmBy"},{"type":"tableCell","position":{"start":{"line":1,"column":1},"end":{"line":1,"column":1}},"children":[{"type":"text","value":"Beginner","position":{"start":{"line":1,"column":1},"end":{"line":1,"column":1}},"key":"c9rmk8eEw7"}],"key":"tvKHVFBwue"},{"type":"tableCell","position":{"start":{"line":1,"column":1},"end":{"line":1,"column":1}},"children":[{"type":"text","value":"This chapter gives a useful overview of collaboration tools which can be deployed in an ambassador scheme","position":{"start":{"line":1,"column":1},"end":{"line":1,"column":1}},"key":"zGQnaSoNQQ"}],"key":"YizqICwGEQ"}],"key":"FN8Xj0T0MN"}],"key":"tnaBQpraQv"},{"type":"container","kind":"figure","children":[{"type":"image","url":"/build/peer-learning-e3a29c546d41d0a42998b818bece07d7.jpeg","alt":"Scriberia illustration showing an ambassador or scholar in action in these types of schemes. On the left hand side of the image is a woman in a graduation gown shaking hands with a glass type structure representing an organisation. On the right hand side of the image the woman is seen in a few different settings- working at a computer, brainstorming ideas and chatting with others and talking about the glass structure- therefore spreading the word about the organisation she is part of through the scheme.","height":"500px","urlSource":"../../figures/peer-learning.jpeg","key":"WWGaEwwf0e"},{"type":"caption","children":[{"type":"paragraph","position":{"start":{"line":19,"column":1},"end":{"line":20,"column":1}},"children":[{"type":"captionNumber","kind":"figure","label":"peer-learning","identifier":"peer-learning","html_id":"peer-learning","enumerator":"1","children":[{"type":"text","value":"Figure ","key":"FRCQoXgE7S"},{"type":"text","value":"1","key":"OxA1CiuvcJ"},{"type":"text","value":":","key":"YA979bfNja"}],"template":"Figure %s:","key":"NJuQMhdV8p"},{"type":"text","value":"Ambassador Schemes\n","position":{"start":{"line":19,"column":1},"end":{"line":19,"column":1}},"key":"Mu8EzGehPZ"},{"type":"emphasis","position":{"start":{"line":19,"column":1},"end":{"line":19,"column":1}},"children":[{"type":"text","value":"The Turing Way","position":{"start":{"line":19,"column":1},"end":{"line":19,"column":1}},"key":"jtU2J1KFb5"}],"key":"BJGoZLwx6K"},{"type":"text","value":" project illustration by Scriberia. Used under a CC-BY 4.0 licence. Original version on Zenodo. ","position":{"start":{"line":19,"column":1},"end":{"line":19,"column":1}},"key":"yk9LDrFILu"},{"type":"cite","url":"https://doi.org/10.5281/zenodo.3332807","position":{"start":{"line":19,"column":1},"end":{"line":19,"column":1}},"children":[{"type":"text","value":"The Turing Way Community & Scriberia (2024)","key":"U1iwxdDU40"}],"kind":"narrative","label":"https://doi.org/10.5281/zenodo.3332807","identifier":"https://doi.org/10.5281/zenodo.3332807","enumerator":"1","key":"xNtSghWQUf"}],"key":"u9vvQTETgP"}],"key":"SJ05ejNQRA"}],"label":"peer-learning","identifier":"peer-learning","enumerator":"1","html_id":"peer-learning","key":"nMZJIj08zS"},{"type":"heading","depth":2,"position":{"start":{"line":24,"column":1},"end":{"line":24,"column":1}},"children":[{"type":"text","value":"Summary","position":{"start":{"line":24,"column":1},"end":{"line":24,"column":1}},"key":"QJrJ3XwEll"}],"label":"cl-ambassador-schemes-summary","identifier":"cl-ambassador-schemes-summary","html_id":"cl-ambassador-schemes-summary","key":"lmmxVaWgnQ"},{"type":"paragraph","position":{"start":{"line":26,"column":1},"end":{"line":28,"column":1}},"children":[{"type":"text","value":"Ambassador schemes are growing in prevalence in data science settings.\nIn academic and related organisations, they are programmes that allow external researchers to develop skills or small projects and become part of that organisation’s community.\nOften these schemes focus on supporting early career researchers.","position":{"start":{"line":26,"column":1},"end":{"line":26,"column":1}},"key":"bnPJRUiC3U"}],"key":"bqzENmPpGe"},{"type":"paragraph","position":{"start":{"line":30,"column":1},"end":{"line":32,"column":1}},"children":[{"type":"text","value":"To be successful, these schemes require careful planning and consideration to ensure participants engage with the scheme, feel supported and also that the scheme is mutually beneficial.\nAmbassadors may receive training or mentorship to effectively carry out their responsibilities.\nAmbassadors often play a crucial role in building positive relationships and conveying the values and strengths of the community they have joined within their own organisations and other related communities.","position":{"start":{"line":30,"column":1},"end":{"line":30,"column":1}},"key":"YU5d6gGmfI"}],"key":"bQBnr7SDzJ"},{"type":"paragraph","position":{"start":{"line":34,"column":1},"end":{"line":35,"column":1}},"children":[{"type":"text","value":"We recognise that the term ‘ambassador scheme’ does not have one definition and can span more widely, such as a ‘brand ambassador’ in corporate settings, so we are using the term ‘ambassador scheme’ as defined above for the purposes of this chapter.\nWe also are aware that these schemes can have a number of synonyms such as fellow, scholar, champion, but for this chapter we will be using the term ambassador.","position":{"start":{"line":34,"column":1},"end":{"line":34,"column":1}},"key":"rXiIQ7Mxdg"}],"key":"PfPyZkl8fe"},{"type":"heading","depth":2,"position":{"start":{"line":38,"column":1},"end":{"line":38,"column":1}},"children":[{"type":"text","value":"Motivation and Background","position":{"start":{"line":38,"column":1},"end":{"line":38,"column":1}},"key":"hgVkom4pSJ"}],"label":"cl-ambassador-schemes-motivation","identifier":"cl-ambassador-schemes-motivation","html_id":"cl-ambassador-schemes-motivation","key":"jtQxpUlbIl"},{"type":"paragraph","position":{"start":{"line":40,"column":1},"end":{"line":42,"column":1}},"children":[{"type":"text","value":"An increasing number of data science related organisations, such as the ","position":{"start":{"line":40,"column":1},"end":{"line":40,"column":1}},"key":"FtZ3v5krTP"},{"type":"link","url":"https://www.software.ac.uk/programmes/fellowship-programme","position":{"start":{"line":40,"column":1},"end":{"line":40,"column":1}},"children":[{"type":"text","value":"Software Sustainability Institute","position":{"start":{"line":40,"column":1},"end":{"line":40,"column":1}},"key":"dqheH0feKL"}],"urlSource":"https://www.software.ac.uk/programmes/fellowship-programme","key":"axgiPNYrgQ"},{"type":"text","value":", ","position":{"start":{"line":40,"column":1},"end":{"line":40,"column":1}},"key":"Iw2oaROkCk"},{"type":"link","url":"https://elixiruknode.org/activities/fellowship/","position":{"start":{"line":40,"column":1},"end":{"line":40,"column":1}},"children":[{"type":"text","value":"ELIXIR","position":{"start":{"line":40,"column":1},"end":{"line":40,"column":1}},"key":"zDktXrySmX"}],"urlSource":"https://elixiruknode.org/activities/fellowship/","key":"cMSFiE9KJj"},{"type":"text","value":" and ","position":{"start":{"line":40,"column":1},"end":{"line":40,"column":1}},"key":"Mhhmz03IeK"},{"type":"link","url":"https://www.widsworldwide.org/join-us/ambassador-program/","position":{"start":{"line":40,"column":1},"end":{"line":40,"column":1}},"children":[{"type":"text","value":"Women in Data Science Worldwide","position":{"start":{"line":40,"column":1},"end":{"line":40,"column":1}},"key":"JFK4yhF7mU"}],"urlSource":"https://www.widsworldwide.org/join-us/ambassador-program/","key":"BX5XwDApUa"},{"type":"text","value":" have developed and launched successful schemes of this nature.\nThe ","position":{"start":{"line":40,"column":1},"end":{"line":40,"column":1}},"key":"pyhAt0qILs"},{"type":"link","url":"https://www.turing.ac.uk/research/research-projects/alan-turing-institute-roche-strategic-partnership","position":{"start":{"line":40,"column":1},"end":{"line":40,"column":1}},"children":[{"type":"text","value":"Turing-Roche Partnership","position":{"start":{"line":40,"column":1},"end":{"line":40,"column":1}},"key":"hcx3TpPKX6"}],"urlSource":"https://www.turing.ac.uk/research/research-projects/alan-turing-institute-roche-strategic-partnership","key":"HDRPXOm2TR"},{"type":"text","value":" launched its ","position":{"start":{"line":40,"column":1},"end":{"line":40,"column":1}},"key":"sIjEyD3ENa"},{"type":"link","url":"https://www.turing.ac.uk/research/research-projects/alan-turing-institute-roche-strategic-partnership/community-scholars","position":{"start":{"line":40,"column":1},"end":{"line":40,"column":1}},"children":[{"type":"text","value":"Community Scholar Scheme","position":{"start":{"line":40,"column":1},"end":{"line":40,"column":1}},"key":"FH1Ercmd0c"}],"urlSource":"https://www.turing.ac.uk/research/research-projects/alan-turing-institute-roche-strategic-partnership/community-scholars","key":"NTlrPk00q2"},{"type":"text","value":" in September 2023 and the team wanted to share their experiences and learnings from developing and running this scheme in the Turing Way as well as hearing from others.\nWe hope this chapter will be a useful starting point for anyone looking to establish their own ambassador scheme.","position":{"start":{"line":40,"column":1},"end":{"line":40,"column":1}},"key":"NIyyIeQCY2"}],"key":"C3SCz1oLsi"},{"type":"paragraph","position":{"start":{"line":44,"column":1},"end":{"line":44,"column":1}},"children":[{"type":"text","value":"Although there are often similar aspects to these schemes, they can vary widely in practice and we would encourage anyone who runs or has been part of one of these schemes to contribute a case study to this chapter on their experiences.","position":{"start":{"line":44,"column":1},"end":{"line":44,"column":1}},"key":"TnVGWkwgtr"}],"key":"qVMqu9dkYY"}],"key":"UYPoiifkDw"}],"key":"N0329PBjVU"},"references":{"cite":{"order":["https://doi.org/10.5281/zenodo.3332807"],"data":{"https://doi.org/10.5281/zenodo.3332807":{"label":"https://doi.org/10.5281/zenodo.3332807","enumerator":"1","doi":"10.5281/ZENODO.3332807","html":"The Turing Way Community, & Scriberia. (2024). <i>Illustrations from The Turing Way: Shared under CC-BY 4.0 for reuse</i>. Zenodo. <a target=\"_blank\" rel=\"noreferrer\" href=\"https://doi.org/10.5281/ZENODO.3332807\">10.5281/ZENODO.3332807</a>","url":"https://doi.org/10.5281/ZENODO.3332807"}}}},"footer":{"navigation":{"prev":{"title":"Online Resources","url":"/collaboration/academic-industry/online-resources-best-practices","group":"The Turing Way"},"next":{"title":"Establishing and Running an Ambassador Scheme","url":"/collaboration/ambassador-schemes/ambassador-schemes-establish","group":"The Turing Way"}}},"domain":"http://localhost:3001"}