[{"author":[{"given":"David","family":"Leslie"}],"DOI":"10.5281/ZENODO.3240529","type":"article-journal","id":"https://doi.org/10.5281/zenodo.3240529","citation-key":"https://doi.org/10.5281/zenodo.3240529","issued":{"date-parts":[[2019]]},"keyword":"The Alan Turing Institute,Public policy,AI,Ethics,Safety,Guidance,Government","language":"en","publisher":"Zenodo","title":"Understanding artificial intelligence ethics and safety: A guide for the responsible design and implementation of AI systems in the public sector","URL":"https://zenodo.org/record/3240529","_graph":[{"type":"@biblatex/text","data":"@article{https://doi.org/10.5281/zenodo.3240529,\n  doi = {10.5281/ZENODO.3240529},\n  url = {https://zenodo.org/record/3240529},\n  author = {Leslie, David},\n  keywords = {The Alan Turing Institute, Public policy, AI, Ethics, Safety, Guidance, Government},\n  language = {en},\n  title = {Understanding artificial intelligence ethics and safety: A guide for the responsible design and implementation of AI systems in the public sector},\n  publisher = {Zenodo},\n  year = {2019},\n  copyright = {Creative Commons Attribution Non Commercial Share Alike 4.0 International}\n}\n"},{"type":"@biblatex/entries+list"},{"type":"@csl/list+object"}]}]