{"version":1,"kind":"Article","sha256":"54ba8ac5cf4dcb1f8008add06ca091fecb3ec3525b7e68b6622721c8a342e650","slug":"reproducible-research.reviewing","location":"/reproducible-research/reviewing.md","dependencies":[],"frontmatter":{"title":"Code Reviewing Process","content_includes_title":false,"authors":[{"nameParsed":{"literal":"The Turing Way Community","given":"The Turing Way","family":"Community"},"name":"The Turing Way Community","id":"contributors-myst-generated-uid-0"}],"license":{"content":{"id":"CC-BY-4.0","url":"https://creativecommons.org/licenses/by/4.0/","name":"Creative Commons Attribution 4.0 International","free":true,"CC":true},"code":{"id":"MIT","url":"https://opensource.org/licenses/MIT","name":"MIT License","free":true,"osi":true}},"github":"https://github.com/the-turing-way/the-turing-way","copyright":"2019-2025","numbering":{"title":{"offset":1}},"edit_url":"https://github.com/the-turing-way/the-turing-way/blob/main/book/website/reproducible-research/reviewing.md","thumbnail":"/bug-catching-c1c19e507df0ae01b34900bd8a4ca5df.png","exports":[{"format":"md","filename":"reviewing.md","url":"/reviewing-997782caafacbca47453a90396a17118.md"}]},"mdast":{"type":"root","children":[{"type":"block","children":[{"type":"heading","depth":2,"position":{"start":{"line":5,"column":1},"end":{"line":5,"column":1}},"children":[{"type":"text","value":"Prerequisites","position":{"start":{"line":5,"column":1},"end":{"line":5,"column":1}},"key":"LIUVhZieo4"}],"label":"rr-reviewing-prerequisites","identifier":"rr-reviewing-prerequisites","html_id":"rr-reviewing-prerequisites","key":"p6HDwsoiak"},{"type":"table","position":{"start":{"line":7,"column":1},"end":{"line":9,"column":1}},"children":[{"type":"tableRow","position":{"start":{"line":7,"column":1},"end":{"line":7,"column":1}},"children":[{"type":"tableCell","header":true,"position":{"start":{"line":7,"column":1},"end":{"line":7,"column":1}},"children":[{"type":"text","value":"Prerequisite","position":{"start":{"line":7,"column":1},"end":{"line":7,"column":1}},"key":"Z9H5L9GKEF"}],"key":"nGIIrm9ofL"},{"type":"tableCell","header":true,"position":{"start":{"line":7,"column":1},"end":{"line":7,"column":1}},"children":[{"type":"text","value":"Importance","position":{"start":{"line":7,"column":1},"end":{"line":7,"column":1}},"key":"xw7m7cx1Rx"}],"key":"EVMZaQ4i5W"},{"type":"tableCell","header":true,"position":{"start":{"line":7,"column":1},"end":{"line":7,"column":1}},"children":[{"type":"text","value":"Notes","position":{"start":{"line":7,"column":1},"end":{"line":7,"column":1}},"key":"da0uyrcQD1"}],"key":"NbfxIdN6yd"}],"key":"cQEbc7uNOJ"},{"type":"tableRow","position":{"start":{"line":9,"column":1},"end":{"line":9,"column":1}},"children":[{"type":"tableCell","position":{"start":{"line":9,"column":1},"end":{"line":9,"column":1}},"children":[{"type":"link","kind":"ref","identifier":"rr-vcs","label":"rr-vcs","children":[{"type":"text","value":"Version Control","key":"l7GgUg1pO9"}],"url":"/reproducible-research/vcs","internal":true,"dataUrl":"/reproducible-research.vcs.json","key":"f2oXTRAMme"}],"key":"WqfLxT3kh9"},{"type":"tableCell","position":{"start":{"line":1,"column":1},"end":{"line":1,"column":1}},"children":[{"type":"text","value":"Necessary","position":{"start":{"line":1,"column":1},"end":{"line":1,"column":1}},"key":"NtYiJFFacu"}],"key":"gXZmhERamC"},{"type":"tableCell","position":{"start":{"line":1,"column":1},"end":{"line":1,"column":1}},"children":[{"type":"text","value":"Understanding the way that ","position":{"start":{"line":1,"column":1},"end":{"line":1,"column":1}},"key":"PKfjiGsPqB"},{"type":"link","url":"https://github.com","position":{"start":{"line":1,"column":1},"end":{"line":1,"column":1}},"children":[{"type":"text","value":"GitHub","position":{"start":{"line":1,"column":1},"end":{"line":1,"column":1}},"key":"wl3tRcounN"}],"urlSource":"https://github.com","key":"KffLEwmmT6"},{"type":"text","value":" arranges its branches, forks, and pull requests within repositories is needed.","position":{"start":{"line":1,"column":1},"end":{"line":1,"column":1}},"key":"zbfRw12WRc"}],"key":"MgT6DMjXsr"}],"key":"K937dUrPLq"}],"key":"jc6xnEtIR8"},{"type":"container","kind":"figure","children":[{"type":"image","url":"/bug-catching-c1c19e507df0ae01b34900bd8a4ca5df.png","alt":"People catching different insects in different ways - representing bugs in our code or project.","height":"500px","urlSource":"../../figures/bug-catching.png","key":"EeR96ox258"},{"type":"caption","children":[{"type":"paragraph","position":{"start":{"line":17,"column":1},"end":{"line":17,"column":1}},"children":[{"type":"captionNumber","kind":"figure","label":"bug-catching","identifier":"bug-catching","html_id":"bug-catching","enumerator":"1","children":[{"type":"text","value":"Figure ","key":"WmWMiucS17"},{"type":"text","value":"1","key":"Q5P5LdjcRS"},{"type":"text","value":":","key":"ayoei1zPFa"}],"template":"Figure %s:","key":"nwftxmx2H7"},{"type":"text","value":"Catching bugs. ","position":{"start":{"line":17,"column":1},"end":{"line":17,"column":1}},"key":"RJxmHr0Msg"},{"type":"emphasis","position":{"start":{"line":17,"column":1},"end":{"line":17,"column":1}},"children":[{"type":"text","value":"The Turing Way","position":{"start":{"line":17,"column":1},"end":{"line":17,"column":1}},"key":"OO5Vdc5xmZ"}],"key":"zZ56qbe6eJ"},{"type":"text","value":" project illustration by Scriberia. Used under a CC-BY 4.0 licence. DOI: ","position":{"start":{"line":17,"column":1},"end":{"line":17,"column":1}},"key":"GPcfRUiRPH"},{"type":"cite","url":"https://doi.org/10.5281/zenodo.3332807","position":{"start":{"line":17,"column":1},"end":{"line":17,"column":1}},"children":[{"type":"text","value":"The Turing Way Community & Scriberia (2024)","key":"jkltrL7nSJ"}],"kind":"narrative","label":"https://doi.org/10.5281/zenodo.3332807","identifier":"https://doi.org/10.5281/zenodo.3332807","enumerator":"1","key":"f5rXCzKEr5"},{"type":"text","value":".","position":{"start":{"line":17,"column":1},"end":{"line":17,"column":1}},"key":"HnXylZkRb0"}],"key":"tmuBJLbhK3"}],"key":"JB1INhDl7E"}],"label":"bug-catching","identifier":"bug-catching","enumerator":"1","html_id":"bug-catching","key":"OWLUpejFzE"},{"type":"heading","depth":2,"position":{"start":{"line":21,"column":1},"end":{"line":21,"column":1}},"children":[{"type":"text","value":"Summary","position":{"start":{"line":21,"column":1},"end":{"line":21,"column":1}},"key":"C57SwGlEJ7"}],"label":"rr-reviewing-summary","identifier":"rr-reviewing-summary","html_id":"rr-reviewing-summary","key":"wdz0OQgjMa"},{"type":"paragraph","position":{"start":{"line":23,"column":1},"end":{"line":24,"column":1}},"children":[{"type":"text","value":"Code review provides an additional way of testing code quality.\nInstead of relying simply on ","position":{"start":{"line":23,"column":1},"end":{"line":23,"column":1}},"key":"yMDxhiNqK5"},{"type":"link","kind":"ref","identifier":"rr-testing","label":"rr-testing","children":[{"type":"text","value":"tests","key":"FdEYyCrbAe"}],"url":"/reproducible-research/testing","internal":true,"dataUrl":"/reproducible-research.testing.json","key":"bfJFlGwowE"},{"type":"text","value":" which the original author puts together themselves, code review gets another programmer to look over the new code and assess it. The goal is to point out strengths and also potential areas of improvement.","position":{"start":{"line":23,"column":1},"end":{"line":23,"column":1}},"key":"bEHlggTw7Z"}],"key":"uBjUk5PIX4"},{"type":"paragraph","position":{"start":{"line":26,"column":1},"end":{"line":29,"column":1}},"children":[{"type":"text","value":"Code review is often done in pairs, with each reviewer also having some of their code reviewed by their partner.\nDoing this can help programmers to see and discuss issues and alternative approaches to tasks, and to learn new tips and tricks.\nThis also means code review practices are particularly well-suited to projects with more than one contributor making changes, where each is working on different parts of the code.\nNonetheless, even the smallest scale projects can harness these approaches with some creative project management.","position":{"start":{"line":26,"column":1},"end":{"line":26,"column":1}},"key":"WQ6xYGMTwj"}],"key":"aPvhneljqJ"},{"type":"paragraph","position":{"start":{"line":31,"column":1},"end":{"line":31,"column":1}},"children":[{"type":"text","value":"Because of their nature, code reviews act as qualitative - rather than quantitative - tests but are no less valuable for that.","position":{"start":{"line":31,"column":1},"end":{"line":31,"column":1}},"key":"sFRCJv154i"}],"key":"bK8wE12hj2"},{"type":"paragraph","position":{"start":{"line":33,"column":1},"end":{"line":34,"column":1}},"children":[{"type":"text","value":"This section will provide an overview of rationales, best practices, and some possible workflows for code review.\nSome details refer specifically to GitHub’s code review functionality as a powerful and widely-used example of a formal code review system; however, equivalent and very similar systems are available elsewhere (for example, ","position":{"start":{"line":33,"column":1},"end":{"line":33,"column":1}},"key":"inE4tdnVgw"},{"type":"link","url":"https://about.gitlab.com","position":{"start":{"line":33,"column":1},"end":{"line":33,"column":1}},"children":[{"type":"text","value":"GitLab","position":{"start":{"line":33,"column":1},"end":{"line":33,"column":1}},"key":"z181FUZY8g"}],"urlSource":"https://about.gitlab.com","key":"H3rMBZIrOF"},{"type":"text","value":"), and even informal code review practices can also be very beneficial to a project.","position":{"start":{"line":33,"column":1},"end":{"line":33,"column":1}},"key":"RDgiAmIVCx"}],"key":"KFva9f3G6H"}],"key":"cH4wEDFEfA"}],"key":"Tzw4Wc2v0x"},"references":{"cite":{"order":["https://doi.org/10.5281/zenodo.3332807"],"data":{"https://doi.org/10.5281/zenodo.3332807":{"label":"https://doi.org/10.5281/zenodo.3332807","enumerator":"1","doi":"10.5281/ZENODO.3332807","html":"The Turing Way Community, & Scriberia. (2024). <i>Illustrations from The Turing Way: Shared under CC-BY 4.0 for reuse</i>. Zenodo. <a target=\"_blank\" rel=\"noreferrer\" href=\"https://doi.org/10.5281/ZENODO.3332807\">10.5281/ZENODO.3332807</a>","url":"https://doi.org/10.5281/ZENODO.3332807"}}}}}